styleclass/__init__.py
styleclass/classify.py
styleclass/features.py
styleclass/settings.py
styleclass/train.py
styleclass/datasets/test.csv
styleclass/datasets/training.csv
styleclass/models/default.model
styleclass-0.0.5.data/scripts/styleclass_classify
styleclass-0.0.5.data/scripts/styleclass_evaluate
styleclass-0.0.5.data/scripts/styleclass_generate_dataset
styleclass-0.0.5.data/scripts/styleclass_train_model
styleclass-0.0.5.dist-info/LICENSE
styleclass-0.0.5.dist-info/METADATA
styleclass-0.0.5.dist-info/WHEEL
styleclass-0.0.5.dist-info/top_level.txt
styleclass-0.0.5.dist-info/RECORD
