Metadata-Version: 2.1
Name: styleclass
Version: 0.0.5
Summary: Citation style classifier
Home-page: https://gitlab.com/crossref/citation_style_classifier
Author: Crossref
Author-email: labs@crossref.org
License: UNKNOWN
Platform: UNKNOWN
Classifier: Programming Language :: Python :: 3
Classifier: License :: OSI Approved :: MIT License
Classifier: Operating System :: OS Independent
Requires-Dist: scipy (==1.3.0)
Requires-Dist: numpy (==1.16.4)
Requires-Dist: pandas (==0.25.0)
Requires-Dist: scikit-learn (==0.21.2)
